encrypt_storage/__init__.py
encrypt_storage/asyncio/__init__.py
encrypt_storage/asyncio/aws_s3.py
encrypt_storage/asyncio/yandex.py
encrypt_storage/encryptor/__init__.py
encrypt_storage/encryptor/abstract.py
encrypt_storage/encryptor/encryptor.py
encrypt_storage/slicer/__init__.py
encrypt_storage/slicer/encrypt.py
encrypt_storage/storages/__init__.py
encrypt_storage/storages/abstract.py
encrypt_storage/storages/aws_s3.py
encrypt_storage/storages/yandex.py
encrypt_storage/types.py
encrypt_storage-0.2.3.dist-info/METADATA
encrypt_storage-0.2.3.dist-info/WHEEL
encrypt_storage-0.2.3.dist-info/RECORD
