Metadata-Version: 2.1
Name: encrypt-storage
Version: 0.2.3
Summary: Позволяет использовать Яндекс диск как хранилище с шифрованием
Home-page: https://github.com/ig-rudenko/encrypt-storage
License: Apache 2.0
Keywords: remote-storage,encryption,yandex-disk,aws-s3,encryption-decryption
Author: ig-rudenko
Author-email: ig.rudenko1@yandex.ru
Requires-Python: >3.9
Classifier: License :: Other/Proprietary License
Classifier: Programming Language :: Python :: 3
Classifier: Programming Language :: Python :: 3.10
Classifier: Programming Language :: Python :: 3.11
Provides-Extra: aws
Requires-Dist: aiofiles (>=23.2.1)
Requires-Dist: aiohttp (>=3.8.6)
Requires-Dist: boto3 (>=1.28.83) ; extra == "aws"
Requires-Dist: botocore (>=1.31.83) ; extra == "aws"
Requires-Dist: cryptography (>=41.0.5)
Requires-Dist: requests (>=2.31.0)
Project-URL: Repository, https://github.com/ig-rudenko/encrypt-storage
